cerbernetix/toolbox/__init__.py
cerbernetix/toolbox/config/__init__.py
cerbernetix/toolbox/config/config.py
cerbernetix/toolbox/config/config_option.py
cerbernetix/toolbox/data/__init__.py
cerbernetix/toolbox/data/mappers.py
cerbernetix/toolbox/data/value_extractor.py
cerbernetix/toolbox/files/__init__.py
cerbernetix/toolbox/files/csv_file.py
cerbernetix/toolbox/files/file.py
cerbernetix/toolbox/files/file_manager.py
cerbernetix/toolbox/files/json_file.py
cerbernetix/toolbox/files/path.py
cerbernetix/toolbox/files/pickle_file.py
cerbernetix/toolbox/logging/__init__.py
cerbernetix/toolbox/logging/config.py
cerbernetix/toolbox/logging/log_file.py
cerbernetix/toolbox/math/__init__.py
cerbernetix/toolbox/math/combination.py
cerbernetix/toolbox/math/utils.py
cerbernetix/toolbox/testing/__init__.py
cerbernetix/toolbox/testing/decorators.py
cerbernetix/toolbox/testing/test_case.py
cerbernetix/toolbox/time/__init__.py
cerbernetix/toolbox/time/weekday.py
cerbernetix.toolbox-0.10.0.dist-info/LICENSE
cerbernetix.toolbox-0.10.0.dist-info/METADATA
cerbernetix.toolbox-0.10.0.dist-info/WHEEL
cerbernetix.toolbox-0.10.0.dist-info/top_level.txt
cerbernetix.toolbox-0.10.0.dist-info/RECORD
