Metadata-Version: 2.1
Name: cerbernetix.toolbox
Version: 0.10.0
Summary: A set of utilities for Python projects
Author-email: Jean-Sébastien CONAN <jsconan@gmail.com>
Project-URL: Homepage, https://github.com/cerbernetix/py-toolbox
Project-URL: Bug Tracker, https://github.com/cerbernetix/py-toolbox/issues
Classifier: Programming Language :: Python :: 3
Classifier: License :: OSI Approved :: MIT License
Classifier: Operating System :: OS Independent
Requires-Python: >=3.7
License-File: LICENSE
Requires-Dist: requests >=2.31.0
Provides-Extra: dev
Requires-Dist: pylint ==2.17.5 ; extra == 'dev'
Provides-Extra: formatting
Requires-Dist: black ==23.9.1 ; extra == 'formatting'
Provides-Extra: linting
Requires-Dist: pylint ==2.17.5 ; extra == 'linting'
Provides-Extra: test
Requires-Dist: coverage ==7.3.1 ; extra == 'test'
